README.rst
manual_requirements.txt
requirements.txt
setup.py
nth_weekday/__init__.py
nth_weekday.egg-info/PKG-INFO
nth_weekday.egg-info/SOURCES.txt
nth_weekday.egg-info/dependency_links.txt
nth_weekday.egg-info/requires.txt
nth_weekday.egg-info/top_level.txt